imgaug/__init__.py
imgaug/computer.py
imgaug/filters.py
imgaug/image.py
imgaug/tests/__init__.py
imgaug/tests/computer_test.py
imgaug/tests/doc_test.py
imgaug/tests/filters_test.py
imgaug/tests/image_test.py
image_augmenter-0.5.5.dist-info/LICENSE
image_augmenter-0.5.5.dist-info/METADATA
image_augmenter-0.5.5.dist-info/WHEEL
image_augmenter-0.5.5.dist-info/top_level.txt
image_augmenter-0.5.5.dist-info/RECORD
