Metadata-Version: 2.1
Name: image-augmenter
Version: 0.5.5
Summary: A tiny python library to augment the images dataset aimed for a ML classification system
Home-page: https://github.com/costajob/image_augmenter
Author: Michele Costa
Author-email: costajob@gmail.com
License: UNKNOWN
Platform: UNKNOWN
Classifier: Programming Language :: Python :: 3.7
Classifier: License :: OSI Approved :: MIT License
Classifier: Operating System :: OS Independent
Requires-Dist: matplotlib (>=3.0)
Requires-Dist: numpy (>=1.16)
Requires-Dist: Pillow (>=5.4)
Requires-Dist: scikit-image (>=0.14)
Requires-Dist: scipy (>=1.2)
